{"type":"FeatureCollection", "features": [
{"type":"Feature","geometry":{"type":"Polygon","coordinates":[[[102.68585913800376,2.231625844692376],[102.68590925427262,2.2329771222943546],[102.68555445857427,2.23301525547695],[102.68548644270832,2.231695324039477],[102.68585913800376,2.231625844692376]]]},"properties":{"name":"Basir Ahmad","description":{"@type":"html","value":"<pre id=\"com.exlyo.mapmarker.description_p_tag\">Calit, bajak,</pre>"},"styleUrl":"#mm_marker_color_235","fill-opacity":1,"fill":"#e91e63","stroke-opacity":1,"stroke":"#e91e63","stroke-width":4,"icon-opacity":1,"icon-color":"#e91e63","icon-scale":1,"com_exlyo_mapmarker_piniconcode":"-1","com_exlyo_mapmarker_customfields":"[]","timestamp":"2025-02-01T05:42:10Z"},"id":"235"},
{"type":"Feature","geometry":{"type":"Polygon","coordinates":[[[102.6868079325892,2.2307757793378014],[102.68633803550853,2.229115295997775],[102.68663933573339,2.22899961903665],[102.68708311347049,2.2305894221943112],[102.6868079325892,2.2307757793378014]]]},"properties":{"name":"Bos","description":{"@type":"html","value":"<pre id=\"com.exlyo.mapmarker.description_p_tag\"></pre>"},"styleUrl":"#mm_marker_color_60","fill-opacity":1,"fill":"#71b300","stroke-opacity":1,"stroke":"#71b300","stroke-width":4,"icon-opacity":1,"icon-color":"#71b300","icon-scale":1,"com_exlyo_mapmarker_piniconcode":"-1","com_exlyo_mapmarker_customfields":"[]","timestamp":"2024-07-30T04:02:20Z"},"id":"60"},
{"type":"Feature","geometry":{"type":"Polygon","coordinates":[[[102.68665342437667,2.2289927936220524],[102.68688972730686,2.228898684445566],[102.68727742195661,2.2299894994819365],[102.68739684359626,2.230382777350513],[102.68709877737379,2.2305828379625487],[102.68665342437667,2.2289927936220524]]]},"properties":{"name":"Bos","description":{"@type":"html","value":"<pre id=\"com.exlyo.mapmarker.description_p_tag\"></pre>"},"styleUrl":"#mm_marker_color_61","fill-opacity":1,"fill":"#71b300","stroke-opacity":1,"stroke":"#71b300","stroke-width":4,"icon-opacity":1,"icon-color":"#71b300","icon-scale":1,"com_exlyo_mapmarker_piniconcode":"-1","com_exlyo_mapmarker_customfields":"[]","timestamp":"2024-07-30T04:02:40Z"},"id":"61"},
{"type":"Feature","geometry":{"type":"Polygon","coordinates":[[[102.68768017815617,2.229794228984264],[102.6872086844703,2.228739099505233],[102.68748547699627,2.228629143771364],[102.68782029078872,2.22930417034328],[102.68797818883704,2.2296695352563516],[102.68768017815617,2.229794228984264]]]},"properties":{"name":"Bos","description":{"@type":"html","value":"<pre id=\"com.exlyo.mapmarker.description_p_tag\"></pre>"},"styleUrl":"#mm_marker_color_44","fill-opacity":1,"fill":"#71b300","stroke-opacity":1,"stroke":"#71b300","stroke-width":4,"icon-opacity":1,"icon-color":"#71b300","icon-scale":1,"com_exlyo_mapmarker_piniconcode":"-1","com_exlyo_mapmarker_customfields":"[]","timestamp":"2024-07-24T12:52:13Z"},"id":"44"},
{"type":"Feature","geometry":{"type":"Polygon","coordinates":[[[102.68562493711656,2.2311382191420597],[102.68545515969224,2.2293469190075332],[102.6856942080726,2.2293195008076014],[102.68591443658303,2.231073334935977],[102.68562493711656,2.2311382191420597]]]},"properties":{"name":"Bos","description":{"@type":"html","value":"<pre id=\"com.exlyo.mapmarker.description_p_tag\"></pre><br/><table border=\"1\"><tr><td>Blok</td><td><pre></pre></td></tr></table>"},"styleUrl":"#mm_marker_color_39","fill-opacity":1,"fill":"#71b300","stroke-opacity":1,"stroke":"#71b300","stroke-width":4,"icon-opacity":1,"icon-color":"#71b300","icon-scale":1,"com_exlyo_mapmarker_piniconcode":"364","com_exlyo_mapmarker_customfields":"[{\"base_params\":{\"id\":\"f5dae5f0-efe3-1057-92c9-5de2637a8eac\",\"field_type\":\"FreeText\",\"is_enabled\":true,\"name\":\"Blok\"},\"value\":{\"text_value\":\"\"}}]","timestamp":"2024-07-24T08:40:58Z"},"id":"39"},
{"type":"Feature","geometry":{"type":"Polygon","coordinates":[[[102.68593495060851,2.231067708622643],[102.68570433534846,2.2293134529302807],[102.68585773825684,2.229285612131219],[102.68611821767301,2.231026395958702],[102.68593495060851,2.231067708622643]]]},"properties":{"name":"Bos","description":{"@type":"html","value":"<pre id=\"com.exlyo.mapmarker.description_p_tag\"></pre><br/><table border=\"1\"><tr><td>Blok</td><td><pre></pre></td></tr></table>"},"styleUrl":"#mm_marker_color_40","fill-opacity":1,"fill":"#71b300","stroke-opacity":1,"stroke":"#71b300","stroke-width":4,"icon-opacity":1,"icon-color":"#71b300","icon-scale":1,"com_exlyo_mapmarker_piniconcode":"364","com_exlyo_mapmarker_customfields":"[{\"base_params\":{\"id\":\"f5dae5f0-efe3-1057-92c9-5de2637a8eac\",\"field_type\":\"FreeText\",\"is_enabled\":true,\"name\":\"Blok\"},\"value\":{\"text_value\":\"\"}}]","timestamp":"2024-07-24T11:57:02Z"},"id":"40"},
{"type":"Feature","geometry":{"type":"Polygon","coordinates":[[[102.68613262909126,2.231002603125207],[102.6858684885383,2.2292813419228295],[102.68603306562538,2.2292193328526726],[102.68638199025426,2.2309445622222936],[102.68613262909126,2.231002603125207]]]},"properties":{"name":"Bos","description":{"@type":"html","value":"<pre id=\"com.exlyo.mapmarker.description_p_tag\"></pre><br/><table border=\"1\"><tr><td>Blok</td><td><pre></pre></td></tr></table>"},"styleUrl":"#mm_marker_color_41","fill-opacity":1,"fill":"#71b300","stroke-opacity":1,"stroke":"#71b300","stroke-width":4,"icon-opacity":1,"icon-color":"#71b300","icon-scale":1,"com_exlyo_mapmarker_piniconcode":"364","com_exlyo_mapmarker_customfields":"[{\"base_params\":{\"id\":\"f5dae5f0-efe3-1057-92c9-5de2637a8eac\",\"field_type\":\"FreeText\",\"is_enabled\":true,\"name\":\"Blok\"},\"value\":{\"text_value\":\"\"}}]","timestamp":"2024-07-24T11:57:31Z"},"id":"41"},
{"type":"Feature","geometry":{"type":"Polygon","coordinates":[[[102.68728493148184,2.229951610681217],[102.6868988752614,2.228866915147597],[102.68719878468615,2.228748417453514],[102.68745821367379,2.2293349797211066],[102.68766375786886,2.2297996163768494],[102.68728493148184,2.229951610681217]]]},"properties":{"name":"Bos","description":{"@type":"html","value":"<pre id=\"com.exlyo.mapmarker.description_p_tag\"></pre>"},"styleUrl":"#mm_marker_color_43","fill-opacity":1,"fill":"#71b300","stroke-opacity":1,"stroke":"#71b300","stroke-width":4,"icon-opacity":1,"icon-color":"#71b300","icon-scale":1,"com_exlyo_mapmarker_piniconcode":"-1","com_exlyo_mapmarker_customfields":"[]","timestamp":"2024-07-24T12:51:55Z"},"id":"43"},
{"type":"Feature","geometry":{"type":"Polygon","coordinates":[[[102.68715458671291,2.2307459463551482],[102.68753416209503,2.2322416418625446],[102.68730295636351,2.232515379967379],[102.68688876898656,2.2309021342646025],[102.68715458671291,2.2307459463551482]]]},"properties":{"name":"Bos","description":{"@type":"html","value":"<pre id=\"com.exlyo.mapmarker.description_p_tag\">Calit, bajak, racun</pre>"},"styleUrl":"#mm_marker_color_71","fill-opacity":1,"fill":"#71b300","stroke-opacity":1,"stroke":"#71b300","stroke-width":4,"icon-opacity":1,"icon-color":"#71b300","icon-scale":1,"com_exlyo_mapmarker_piniconcode":"-1","com_exlyo_mapmarker_customfields":"[]","timestamp":"2024-08-01T01:32:13Z"},"id":"71"},
{"type":"Feature","geometry":{"type":"Polygon","coordinates":[[[102.68744751172991,2.2305503203862047],[102.68778046020903,2.232008029785731],[102.68754990809498,2.232249544178798],[102.68716862461694,2.2307325479739823],[102.68744751172991,2.2305503203862047]]]},"properties":{"name":"Bos","description":{"@type":"html","value":"<pre id=\"com.exlyo.mapmarker.description_p_tag\">Calit, bajak, racun</pre>"},"styleUrl":"#mm_marker_color_70","fill-opacity":1,"fill":"#71b300","stroke-opacity":1,"stroke":"#71b300","stroke-width":4,"icon-opacity":1,"icon-color":"#71b300","icon-scale":1,"com_exlyo_mapmarker_piniconcode":"-1","com_exlyo_mapmarker_customfields":"[]","timestamp":"2024-08-01T01:31:27Z"},"id":"70"},
{"type":"Feature","geometry":{"type":"Polygon","coordinates":[[[102.68789776377866,2.23105650924196],[102.68805255812637,2.2317800727591743],[102.68779687157704,2.2320094180613244],[102.6874617867145,2.230538268908498],[102.68776280885213,2.230385851154113],[102.68780230369147,2.230520133765717],[102.68789776377866,2.23105650924196]]]},"properties":{"name":"Bos","description":{"@type":"html","value":"<pre id=\"com.exlyo.mapmarker.description_p_tag\">Calit, bajak, racun</pre>"},"styleUrl":"#mm_marker_color_69","fill-opacity":1,"fill":"#71b300","stroke-opacity":1,"stroke":"#71b300","stroke-width":4,"icon-opacity":1,"icon-color":"#71b300","icon-scale":1,"com_exlyo_mapmarker_piniconcode":"-1","com_exlyo_mapmarker_customfields":"[]","timestamp":"2024-08-01T01:31:03Z"},"id":"69"},
{"type":"Feature","geometry":{"type":"Polygon","coordinates":[[[102.68531310191459,2.231201643078175],[102.68524474992755,2.2293617171017703],[102.68544105954498,2.229359257161788],[102.68560664642558,2.2311338446229514],[102.68531310191459,2.231201643078175]]]},"properties":{"name":"Dalail","description":{"@type":"html","value":"<pre id=\"com.exlyo.mapmarker.description_p_tag\"></pre>"},"styleUrl":"#mm_marker_color_57","fill-opacity":1,"fill":"#e91e63","stroke-opacity":1,"stroke":"#e91e63","stroke-width":4,"icon-opacity":1,"icon-color":"#e91e63","icon-scale":1,"com_exlyo_mapmarker_piniconcode":"-1","com_exlyo_mapmarker_customfields":"[]","timestamp":"2024-07-30T04:00:47Z"},"id":"57"},
{"type":"Feature","geometry":{"type":"Polygon","coordinates":[[[102.6868768835995,2.2309144684428457],[102.6872848910422,2.2325301740577177],[102.68703936851156,2.232721464764224],[102.68663785596486,2.231003668755015],[102.6868768835995,2.2309144684428457]]]},"properties":{"name":"Dedek","description":{"@type":"html","value":"<pre id=\"com.exlyo.mapmarker.description_p_tag\">Calit, bajak,</pre>"},"styleUrl":"#mm_marker_color_231","fill-opacity":1,"fill":"#e91e63","stroke-opacity":1,"stroke":"#e91e63","stroke-width":4,"icon-opacity":1,"icon-color":"#e91e63","icon-scale":1,"com_exlyo_mapmarker_piniconcode":"-1","com_exlyo_mapmarker_customfields":"[]","timestamp":"2025-02-01T05:37:02Z"},"id":"231"},
{"type":"Feature","geometry":{"type":"Polygon","coordinates":[[[102.68472617562917,2.231343414841827],[102.68467959579584,2.229273330324854],[102.68485325026414,2.2293224224885533],[102.68491015219006,2.2312955974613264],[102.68472617562917,2.231343414841827]]]},"properties":{"name":"Fauziah / Jaslan","description":{"@type":"html","value":"<pre id=\"com.exlyo.mapmarker.description_p_tag\"></pre><br/><table border=\"1\"><tr><td>Blok</td><td><pre></pre></td></tr></table>"},"styleUrl":"#mm_marker_color_36","fill-opacity":1,"fill":"#71b300","stroke-opacity":1,"stroke":"#71b300","stroke-width":4,"icon-opacity":1,"icon-color":"#71b300","icon-scale":1,"com_exlyo_mapmarker_piniconcode":"364","com_exlyo_mapmarker_customfields":"[{\"base_params\":{\"id\":\"f5dae5f0-efe3-1057-92c9-5de2637a8eac\",\"field_type\":\"FreeText\",\"is_enabled\":true,\"name\":\"Blok\"},\"value\":{\"text_value\":\"\"}}]","timestamp":"2024-07-24T06:40:55Z"},"id":"36"},
{"type":"Feature","geometry":{"type":"Polygon","coordinates":[[[102.685049164419,2.2293521439638853],[102.68522748852044,2.2293619987565787],[102.68529517113343,2.2312060474317126],[102.68512606471783,2.2312485613805975],[102.685049164419,2.2293521439638853]]]},"properties":{"name":"Habsah","description":{"@type":"html","value":"<pre id=\"com.exlyo.mapmarker.description_p_tag\"></pre><br/><table border=\"1\"><tr><td>Blok</td><td><pre></pre></td></tr></table>"},"styleUrl":"#mm_marker_color_38","fill-opacity":1,"fill":"#71b300","stroke-opacity":1,"stroke":"#71b300","stroke-width":4,"icon-opacity":1,"icon-color":"#71b300","icon-scale":1,"com_exlyo_mapmarker_piniconcode":"364","com_exlyo_mapmarker_customfields":"[{\"base_params\":{\"id\":\"f5dae5f0-efe3-1057-92c9-5de2637a8eac\",\"field_type\":\"FreeText\",\"is_enabled\":true,\"name\":\"Blok\"},\"value\":{\"text_value\":\"\"}}]","timestamp":"2024-07-24T08:21:45Z"},"id":"38"},
{"type":"Feature","geometry":{"type":"Polygon","coordinates":[[[102.68793811813927,2.2295344720571024],[102.68782363326595,2.229280961955905],[102.68749682655569,2.228612224976074],[102.68804203684176,2.228375612304663],[102.68822514299794,2.2286613402543143],[102.6885072085458,2.2291302828662016],[102.68793811813927,2.2295344720571024]]]},"properties":{"name":"Isnin Mahail - Daud","description":{"@type":"html","value":"<pre id=\"com.exlyo.mapmarker.description_p_tag\">Calit, bajak,</pre>"},"styleUrl":"#mm_marker_color_176","fill-opacity":1,"fill":"#e91e63","stroke-opacity":1,"stroke":"#e91e63","stroke-width":4,"icon-opacity":1,"icon-color":"#e91e63","icon-scale":1,"com_exlyo_mapmarker_piniconcode":"-1","com_exlyo_mapmarker_customfields":"[]","timestamp":"2024-11-04T10:03:09Z"},"id":"176"},
{"type":"Feature","geometry":{"type":"Polygon","coordinates":[[[102.68503403589985,2.2293525538089787],[102.68511067616502,2.231251618695363],[102.68493046037624,2.2312956966807653],[102.68486606944734,2.22932455137998],[102.68503403589985,2.2293525538089787]]]},"properties":{"name":"Jaslan","description":{"@type":"html","value":"<pre id=\"com.exlyo.mapmarker.description_p_tag\"></pre><br/><table border=\"1\"><tr><td>Blok</td><td><pre></pre></td></tr></table>"},"styleUrl":"#mm_marker_color_37","fill-opacity":1,"fill":"#71b300","stroke-opacity":1,"stroke":"#71b300","stroke-width":4,"icon-opacity":1,"icon-color":"#71b300","icon-scale":1,"com_exlyo_mapmarker_piniconcode":"364","com_exlyo_mapmarker_customfields":"[{\"base_params\":{\"id\":\"f5dae5f0-efe3-1057-92c9-5de2637a8eac\",\"field_type\":\"FreeText\",\"is_enabled\":true,\"name\":\"Blok\"},\"value\":{\"text_value\":\"\"}}]","timestamp":"2024-07-24T07:46:20Z"},"id":"37"},
{"type":"Feature","geometry":{"type":"Polygon","coordinates":[[[102.68682122241954,2.2318651836364585],[102.687021726401,2.232738799419316],[102.68689727143298,2.232858436177775],[102.6865126022529,2.2329170556227322],[102.68622320780864,2.231100790449133],[102.68661661095496,2.2310228336634155],[102.68682122241954,2.2318651836364585]]]},"properties":{"name":"Kak Mah","description":{"@type":"html","value":"<pre id=\"com.exlyo.mapmarker.description_p_tag\">Calit, bajak, racun</pre>"},"styleUrl":"#mm_marker_color_232","fill-opacity":1,"fill":"#71b300","stroke-opacity":1,"stroke":"#71b300","stroke-width":4,"icon-opacity":1,"icon-color":"#71b300","icon-scale":1,"com_exlyo_mapmarker_piniconcode":"-1","com_exlyo_mapmarker_customfields":"[]","timestamp":"2025-02-01T05:37:49Z"},"id":"232"},
{"type":"Feature","geometry":{"type":"Polygon","coordinates":[[[102.68592603160401,2.2329814085063666],[102.68587670547544,2.231192101763915],[102.68618581472394,2.2311061130011747],[102.68648197135553,2.232906523210154],[102.68592603160401,2.2329814085063666]]]},"properties":{"name":"Kak mah","description":{"@type":"html","value":"<pre id=\"com.exlyo.mapmarker.description_p_tag\">Calit, bajak, racun</pre>"},"styleUrl":"#mm_marker_color_233","fill-opacity":1,"fill":"#71b300","stroke-opacity":1,"stroke":"#71b300","stroke-width":4,"icon-opacity":1,"icon-color":"#71b300","icon-scale":1,"com_exlyo_mapmarker_piniconcode":"-1","com_exlyo_mapmarker_customfields":"[]","timestamp":"2025-02-01T05:38:41Z"},"id":"233"},
{"type":"Feature","geometry":{"type":"Polygon","coordinates":[[[102.68487430467248,2.2313812146806256],[102.68499532754409,2.2330688550182813],[102.6846502801436,2.2331150188207696],[102.68458667523694,2.232901263491039],[102.68457816463483,2.2327283605443955],[102.68454689351915,2.2325355234465674],[102.6845220566655,2.2314635862425205],[102.68487430467248,2.2313812146806256]]]},"properties":{"name":"Marker 27","description":{"@type":"html","value":"<pre id=\"com.exlyo.mapmarker.description_p_tag\">Calit, bajak, racun</pre><br/><table border=\"1\"><tr><td>Blok</td><td><pre></pre></td></tr><tr><td>Blok</td><td><pre></pre></td></tr></table>"},"styleUrl":"#mm_marker_color_42","fill-opacity":1,"fill":"#71b300","stroke-opacity":1,"stroke":"#71b300","stroke-width":4,"icon-opacity":1,"icon-color":"#71b300","icon-scale":1,"com_exlyo_mapmarker_piniconcode":"364","com_exlyo_mapmarker_customfields":"[{\"base_params\":{\"id\":\"f5dae5f0-efe3-1057-92c9-5de2637a8eac\",\"field_type\":\"FreeText\",\"is_enabled\":true,\"name\":\"Blok\"},\"value\":{\"text_value\":\"\"}},{\"base_params\":{\"id\":\"f5dae5f0-efe3-1057-92c9-5de2637a8eac\",\"field_type\":\"FreeText\",\"is_enabled\":true,\"name\":\"Blok\"},\"value\":{\"text_value\":\"\"}}]","timestamp":"2024-07-24T11:59:36Z"},"id":"42"},
{"type":"Feature","geometry":{"type":"Polygon","coordinates":[[[102.6881323886104,2.2299690760845863],[102.68794198987653,2.2295476058040964],[102.68852453102417,2.2291369244873964],[102.68879215729999,2.2295440300967924],[102.6881323886104,2.2299690760845863]]]},"properties":{"name":"Marker 112","description":{"@type":"html","value":"<pre id=\"com.exlyo.mapmarker.description_p_tag\"></pre>"},"styleUrl":"#mm_marker_color_175","fill-opacity":1,"fill":"#e91e63","stroke-opacity":1,"stroke":"#e91e63","stroke-width":4,"icon-opacity":1,"icon-color":"#e91e63","icon-scale":1,"com_exlyo_mapmarker_piniconcode":"-1","com_exlyo_mapmarker_customfields":"[]","timestamp":"2024-11-04T09:25:28Z"},"id":"175"},
{"type":"Feature","geometry":{"type":"Polygon","coordinates":[[[102.6845161966438,2.231354752610277],[102.68450700235603,2.2291763603556243],[102.68466071242355,2.22927173595704],[102.68471206872876,2.231336909210973],[102.6845161966438,2.231354752610277]]]},"properties":{"name":"Mat yah","description":{"@type":"html","value":"<pre id=\"com.exlyo.mapmarker.description_p_tag\"></pre>"},"styleUrl":"#mm_marker_color_62","fill-opacity":1,"fill":"#e91e63","stroke-opacity":1,"stroke":"#e91e63","stroke-width":4,"icon-opacity":1,"icon-color":"#e91e63","icon-scale":1,"com_exlyo_mapmarker_piniconcode":"-1","com_exlyo_mapmarker_customfields":"[]","timestamp":"2024-07-30T04:04:26Z"},"id":"62"},
{"type":"Feature","geometry":{"type":"Polygon","coordinates":[[[102.68639907914044,2.2309393324178597],[102.68604603272657,2.2292067011394803],[102.68617246851205,2.2291561052476814],[102.68658580800306,2.2308771753772314],[102.68639907914044,2.2309393324178597]]]},"properties":{"name":"Otok - Mister Ali","description":{"@type":"html","value":"<pre id=\"com.exlyo.mapmarker.description_p_tag\"></pre>"},"styleUrl":"#mm_marker_color_58","fill-opacity":1,"fill":"#e91e63","stroke-opacity":1,"stroke":"#e91e63","stroke-width":4,"icon-opacity":1,"icon-color":"#e91e63","icon-scale":1,"com_exlyo_mapmarker_piniconcode":"-1","com_exlyo_mapmarker_customfields":"[]","timestamp":"2024-07-30T04:01:34Z"},"id":"58"},
{"type":"Feature","geometry":{"type":"Polygon","coordinates":[[[102.68660581741742,2.230886977009014],[102.68618339011896,2.2291500505993542],[102.68631961821565,2.229100038434451],[102.68679528511096,2.230772649173767],[102.68660581741742,2.230886977009014]]]},"properties":{"name":"Petai","description":{"@type":"html","value":"<pre id=\"com.exlyo.mapmarker.description_p_tag\"></pre>"},"styleUrl":"#mm_marker_color_59","fill-opacity":1,"fill":"#71b300","stroke-opacity":1,"stroke":"#71b300","stroke-width":4,"icon-opacity":1,"icon-color":"#71b300","icon-scale":1,"com_exlyo_mapmarker_piniconcode":"-1","com_exlyo_mapmarker_customfields":"[]","timestamp":"2024-07-30T04:02:04Z"},"id":"59"},
{"type":"Feature","geometry":{"type":"Polygon","coordinates":[[[102.68544027080877,2.2312587373317845],[102.68553253998554,2.2330134741003955],[102.68502857209268,2.233083010808826],[102.68489532600691,2.23138361222114],[102.68544027080877,2.2312587373317845]]]},"properties":{"name":"Suhaidep","description":{"@type":"html","value":"<pre id=\"com.exlyo.mapmarker.description_p_tag\">Calit, bajak,</pre><br/><table border=\"1\"><tr><td>Blok</td><td><pre></pre></td></tr></table>"},"styleUrl":"#mm_marker_color_298","fill-opacity":1,"fill":"#e91e63","stroke-opacity":1,"stroke":"#e91e63","stroke-width":4,"icon-opacity":1,"icon-color":"#e91e63","icon-scale":1,"com_exlyo_mapmarker_piniconcode":"-1","com_exlyo_mapmarker_customfields":"[{\"base_params\":{\"id\":\"f5dae5f0-efe3-1057-92c9-5de2637a8eac\",\"field_type\":\"FreeText\",\"is_enabled\":true,\"name\":\"Blok\"},\"value\":{\"text_value\":\"\"}}]","timestamp":"2025-04-25T23:13:19Z"},"id":"298"},
{"type":"Feature","geometry":{"type":"Polygon","coordinates":[[[102.68824415361848,2.230865330976],[102.68848448946227,2.2316517724082283],[102.68811894484286,2.231762392404785],[102.68794591693857,2.230973626148911],[102.68796820847267,2.230928408320151],[102.68824415361848,2.230865330976]]]},"properties":{"name":"Tapak Semai Pasir","description":{"@type":"html","value":"<pre id=\"com.exlyo.mapmarker.description_p_tag\"></pre>"},"styleUrl":"#mm_marker_color_234","fill-opacity":1,"fill":"#71b300","stroke-opacity":1,"stroke":"#71b300","stroke-width":4,"icon-opacity":1,"icon-color":"#71b300","icon-scale":1,"com_exlyo_mapmarker_piniconcode":"-1","com_exlyo_mapmarker_customfields":"[]","timestamp":"2025-02-01T05:41:20Z"},"id":"234"},
{"type":"Feature","geometry":{"type":"Polygon","coordinates":[[[102.68803262821889,2.230344455447543],[102.68816504813442,2.23072337408114],[102.68797422308248,2.2307820216376717],[102.68785150865062,2.230405514856347],[102.68803262821889,2.230344455447543]]]},"properties":{"name":"Tapak Semai Simen","description":{"@type":"html","value":"<pre id=\"com.exlyo.mapmarker.description_p_tag\">0.23 acre</pre>"},"styleUrl":"#mm_marker_color_143","fill-opacity":1,"fill":"#71b300","stroke-opacity":1,"stroke":"#71b300","stroke-width":4,"icon-opacity":1,"icon-color":"#71b300","icon-scale":1,"com_exlyo_mapmarker_piniconcode":"-1","com_exlyo_mapmarker_customfields":"[]","timestamp":"2024-10-22T08:59:42Z"},"id":"143"}
]}